Verilog-Logic-Gates/ALU.v
module ALU (ALUctl, A, B, ALUOut, Zero);
	input [3:0] ALUctl;
	input [7:0] A,B;
	output reg [7:0] ALUOut;
	output Zero;
	assign Zero = (ALUOut == 0); //Zero is true if ALUOut is 0
	always @(ALUctl, A,B) //reevaluate if these change
	case (ALUctl)
		0: ALUOut <= A & B;
		1: ALUOut <= A | B;
		2: ALUOut <= A + B;
		6: ALUOut <= A - B;
		7: ALUOut <= A < B ? 1:0;
		12: ALUOut <= ~(A | B); // result is nor
		default: ALUOut <= 0; // should not happen
	endcase
endmodule

Verilog-Logic-Gates/ALU_tb.v
//ALU_tb.v test bench for ALU
module ALU_tb;
	reg[3:0] in;
	reg [7:0] a,b;
	wire [7:0] out;

        // duration for each bit = 20 * timescale = 20 * 1 ns  = 20ns
        localparam period = 20;  

    ALU UUT (.ALUctl(in),  .A(a), .B(b), .ALUOut(out)); 
    initial begin // initial block executes only once
     $dumpfile("ALU.vcd");
     $dumpvars(0,UUT);

// Note : For most gates I will do a =1, b= 0 
// but will not waste time with a = 0, b=1 
// It only makes sense to do it for a - b or a < b
	    // a and b
	    a = 0;
	    b = 0;
	    in = 0;
            #period; // wait for period 
	    
	    a = 1;
	    b = 0;
	    #period 

	    a = 1;
	    b = 1;
	    #period; 

	    // a or b
	    a = 0;
	    b = 0;
	    in = 1;
            #period;

	    a = 1;
	    b = 0;
	    #period;

	    a = 1;
	    b = 1;
	    #period

	    // a + b
	    in = 2;
	    a = 0;
	    b = 0;
	    #period;

	    a = 1;
	    b = 0;
	    #period;

	    a = 1;
	    b = 1;
	    #period;


	    // a - b
            in = 6;
	    a = 0;
	    b = 0;
	    #period;

	    a = 1;
	    b = 0;
	    #period;

	    a = 0;
	    b = 1;
	    #period;


	    a = 1;
	    b = 1;
	    #period;
	   
        
    	   // a < b ? 1 : 0
	   in = 7;
	    a = 0;
	    b = 0;
	    #period;

	    a = 1;
	    b = 0;
	    #period;

	    a = 0;
	    b = 1;
	    #period;


	    a = 1;
	    b = 1;
	    #period;
	   
	   // NOT( a or b)
	   in =12;
	    a = 0;
	    b = 0;
	    #period;

	    a = 1;
	    b = 0;
	    #period;

	    a = 1;
	    b = 1;
	    #period;

    	end

endmodule

Verilog-Logic-Gates/ALU.vcd
$date
	Thu Oct 27 13:06:42 2022
$end
$version
	Icarus Verilog
$end
$timescale
	1s
$end
$scope module ALU_tb $end
$scope module UUT $end
$var wire 8 ! A [7:0] $end
$var wire 4 " ALUctl [3:0] $end
$var wire 8 # B [7:0] $end
$var wire 1 $ Zero $end
$var reg 8 % ALUOut [7:0] $end
$upscope $end
$upscope $end
$enddefinitions $end
$comment Show the parameter values. $end
$dumpall
$end
#0
$dumpvars
b0 %
1$
b0 #
b0 "
b0 !
$end
#20
b1 !
#40
0$
b1 %
b1 #
#60
1$
b0 %
b1 "
b0 #
b0 !
#80
0$
b1 %
b1 !
#100
b1 #
#120
1$
b0 %
b0 #
b0 !
b10 "
#140
0$
b1 %
b1 !
#160
b10 %
b1 #
#180
1$
b0 %
b0 #
b0 !
b110 "
#200
0$
b1 %
b1 !
#220
b11111111 %
b1 #
b0 !
#240
1$
b0 %
b1 !
#260
b0 #
b0 !
b111 "
#280
b1 !
#300
0$
b1 %
b1 #
b0 !
#320
1$
b0 %
b1 !
#340
0$
b11111111 %
b0 #
b0 !
b1100 "
#360
b11111110 %
b1 !
#380
b1 #
